{
  "users": [
    {
      "id": 1,
      "email": "user1@example.com",
      "password": "password1",
      "nickname": "userOne"
    },
    {
      "id": 2,
      "email": "user2@example.com",
      "password": "password2",
      "nickname": "userTwo"
    },
    {
      "id": 3,
      "email": "user3@example.com",
      "password": "password3",
      "nickname": "userThree"
    },
    {
      "id": 4,
      "email": "user4@example.com",
      "password": "password4",
      "nickname": "userFour"
    },
    {
      "id": 5,
      "email": "user5@example.com",
      "password": "password5",
      "nickname": "userFive"
    },
    {
      "id": 6,
      "email": "user6@example.com",
      "password": "password6",
      "nickname": "userSix"
    },
    {
      "id": 7,
      "email": "user7@example.com",
      "password": "password7",
      "nickname": "userSeven"
    },
    {
      "id": 8,
      "email": "user8@example.com",
      "password": "password8",
      "nickname": "userEight"
    },
    {
      "id": 9,
      "email": "user9@example.com",
      "password": "password9",
      "nickname": "userNine"
    },
    {
      "id": 10,
      "email": "user10@example.com",
      "password": "password10",
      "nickname": "userTen"
    },
    {
      "id": 11,
      "email": "1",
      "password": "1",
      "nickname": ""
    }
  ],
  "favorites": [
    {
      "id": 1,
      "film_id": [
        1197306
      ],
      "series_id" :[

      ]
    },
    {
      "id": 2,
      "film_id": [
        1197305
      ],
      "series_id": []
    },
    {
      "id": 3,
      "film_id": [
        1197304
      ],
      "series_id": []
    },
    {
      "id": 4,
      "film_id": [
        1197303
      ],
      "series_id": []
    },
    {
      "id": 5,
      "film_id": [
        1197302
      ],
      "series_id": []
    },
    {
      "id": 11,
      "film_id": [
        1197306,
        1197305,
        1197303,
        1197302,
        1197301,
        1197300
      ],
      "series_id": [
        151243,
        12342,
        12444
      ]
    }
  ]
}